bmloader/__init__.py
bmloader/lib/__init__.py
bmloader/lib/nev.py
bmloader/lib/nsx.py
bmloader/lib/utils.py
bmloader-0.0.2.dist-info/LICENSE
bmloader-0.0.2.dist-info/METADATA
bmloader-0.0.2.dist-info/WHEEL
bmloader-0.0.2.dist-info/top_level.txt
bmloader-0.0.2.dist-info/RECORD
